{
  "locked": false,
  "version": -9996,
  "targets": {
    ".NETFramework,Version=v4.5": {},
    ".NETCore,Version=v4.5": {},
    ".NETPlatform,Version=v5.0": {
      "Microsoft.CSharp/4.0.0-beta-23109": {
        "dependencies": {
          "System.Runtime": "4.0.20-beta-23109",
          "System.Dynamic.Runtime": "4.0.0-beta-23109",
          "System.Linq.Expressions": "4.0.0-beta-23109",
          "System.Runtime.InteropServices": "4.0.20-beta-23109",
          "System.Resources.ResourceManager": "4.0.0-beta-23109",
          "System.Linq": "4.0.0-beta-23109",
          "System.Reflection.TypeExtensions": "4.0.0-beta-23109",
          "System.Reflection.Primitives": "4.0.0-beta-23109",
          "System.Reflection.Extensions": "4.0.0-beta-23109",
          "System.Collections": "4.0.10-beta-23109",
          "System.Diagnostics.Debug": "4.0.10-beta-23109",
          "System.Reflection": "4.0.10-beta-23109",
          "System.Threading": "4.0.10-beta-23109",
          "System.Globalization": "4.0.10-beta-23109",
          "System.Runtime.Extensions": "4.0.10-beta-23109",
          "System.ObjectModel": "4.0.10-beta-23109"
        },
        "compile": {
          "ref/dotnet/Microsoft.CSharp.dll": {}
        },
        "runtime": {
          "lib/dotnet/Microsoft.CSharp.dll": {}
        }
      },
      "System.Collections/4.0.10-beta-23109": {
        "dependencies": {
          "System.Runtime": "4.0.0-beta-23109"
        },
        "compile": {
          "ref/dotnet/System.Collections.dll": {}
        }
      },
      "System.Collections.Concurrent/4.0.10-beta-23109": {
        "dependencies": {
          "System.Runtime": "4.0.20-beta-23109",
          "System.Threading.Tasks": "4.0.10-beta-23109",
          "System.Diagnostics.Tracing": "4.0.20-beta-23109",
          "System.Resources.ResourceManager": "4.0.0-beta-23109",
          "System.Diagnostics.Debug": "4.0.10-beta-23109",
          "System.Threading": "4.0.10-beta-23109",
          "System.Collections": "4.0.10-beta-23109",
          "System.Runtime.Extensions": "4.0.10-beta-23109",
          "System.Globalization": "4.0.10-beta-23109"
        },
        "compile": {
          "ref/dotnet/System.Collections.Concurrent.dll": {}
        },
        "runtime": {
          "lib/dotnet/System.Collections.Concurrent.dll": {}
        }
      },
      "System.ComponentModel/4.0.0-beta-23109": {
        "dependencies": {
          "System.Runtime": "4.0.20-beta-23109"
        },
        "compile": {
          "ref/dotnet/System.ComponentModel.dll": {}
        },
        "runtime": {
          "lib/dotnet/System.ComponentModel.dll": {}
        }
      },
      "System.Diagnostics.Debug/4.0.10-beta-23109": {
        "dependencies": {
          "System.Runtime": "4.0.0-beta-23109"
        },
        "compile": {
          "ref/dotnet/System.Diagnostics.Debug.dll": {}
        }
      },
      "System.Diagnostics.Tools/4.0.0-beta-23109": {
        "dependencies": {
          "System.Runtime": "4.0.0-beta-23109"
        },
        "compile": {
          "ref/dotnet/System.Diagnostics.Tools.dll": {}
        }
      },
      "System.Diagnostics.Tracing/4.0.20-beta-23109": {
        "dependencies": {
          "System.Runtime": "4.0.0-beta-23109"
        },
        "compile": {
          "ref/dotnet/System.Diagnostics.Tracing.dll": {}
        }
      },
      "System.Dynamic.Runtime/4.0.0-beta-23109": {
        "dependencies": {
          "System.Linq.Expressions": "4.0.0-beta-23109",
          "System.ObjectModel": "4.0.0-beta-23109",
          "System.Reflection": "4.0.0-beta-23109",
          "System.Runtime": "4.0.0-beta-23109"
        },
        "compile": {
          "ref/dotnet/System.Dynamic.Runtime.dll": {}
        }
      },
      "System.Globalization/4.0.10-beta-23109": {
        "dependencies": {
          "System.Runtime": "4.0.0-beta-23109"
        },
        "compile": {
          "ref/dotnet/System.Globalization.dll": {}
        }
      },
      "System.IO/4.0.0-beta-23109": {
        "dependencies": {
          "System.Runtime": "4.0.0-beta-23109",
          "System.Text.Encoding": "4.0.0-beta-23109",
          "System.Threading.Tasks": "4.0.0-beta-23109"
        },
        "compile": {
          "ref/dotnet/System.IO.dll": {}
        }
      },
      "System.Linq/4.0.0-beta-23109": {
        "dependencies": {
          "System.Runtime": "4.0.20-beta-23109",
          "System.Collections": "4.0.10-beta-23109",
          "System.Resources.ResourceManager": "4.0.0-beta-23109",
          "System.Diagnostics.Debug": "4.0.10-beta-23109",
          "System.Runtime.Extensions": "4.0.10-beta-23109"
        },
        "compile": {
          "ref/dotnet/System.Linq.dll": {}
        },
        "runtime": {
          "lib/dotnet/System.Linq.dll": {}
        }
      },
      "System.Linq.Expressions/4.0.10-beta-23109": {
        "dependencies": {
          "System.Runtime": "4.0.0-beta-23109",
          "System.Reflection": "4.0.0-beta-23109"
        },
        "compile": {
          "ref/dotnet/System.Linq.Expressions.dll": {}
        }
      },
      "System.ObjectModel/4.0.10-beta-23109": {
        "dependencies": {
          "System.Runtime": "4.0.20-beta-23109",
          "System.Resources.ResourceManager": "4.0.0-beta-23109",
          "System.Diagnostics.Debug": "4.0.10-beta-23109",
          "System.Collections": "4.0.10-beta-23109",
          "System.Threading": "4.0.10-beta-23109"
        },
        "compile": {
          "ref/dotnet/System.ObjectModel.dll": {}
        },
        "runtime": {
          "lib/dotnet/System.ObjectModel.dll": {}
        }
      },
      "System.Reflection/4.0.10-beta-23109": {
        "dependencies": {
          "System.Runtime": "4.0.20-beta-23109",
          "System.IO": "4.0.0-beta-23109",
          "System.Reflection.Primitives": "4.0.0-beta-23109"
        },
        "compile": {
          "ref/dotnet/System.Reflection.dll": {}
        }
      },
      "System.Reflection.Extensions/4.0.0-beta-23109": {
        "dependencies": {
          "System.Runtime": "4.0.0-beta-23109",
          "System.Reflection": "4.0.0-beta-23109"
        },
        "compile": {
          "ref/dotnet/System.Reflection.Extensions.dll": {}
        }
      },
      "System.Reflection.Primitives/4.0.0-beta-23109": {
        "dependencies": {
          "System.Runtime": "4.0.0-beta-23109"
        },
        "compile": {
          "ref/dotnet/System.Reflection.Primitives.dll": {}
        }
      },
      "System.Reflection.TypeExtensions/4.0.0-beta-23109": {
        "dependencies": {
          "System.Runtime": "4.0.0-beta-23109",
          "System.Reflection": "4.0.0-beta-23109"
        },
        "compile": {
          "ref/dotnet/System.Reflection.TypeExtensions.dll": {}
        }
      },
      "System.Resources.ResourceManager/4.0.0-beta-23109": {
        "dependencies": {
          "System.Runtime": "4.0.0-beta-23109",
          "System.Reflection": "4.0.0-beta-23109",
          "System.Globalization": "4.0.0-beta-23109"
        },
        "compile": {
          "ref/dotnet/System.Resources.ResourceManager.dll": {}
        }
      },
      "System.Runtime/4.0.20-beta-23109": {
        "compile": {
          "ref/dotnet/System.Runtime.dll": {}
        }
      },
      "System.Runtime.Extensions/4.0.10-beta-23109": {
        "dependencies": {
          "System.Runtime": "4.0.20-beta-23109"
        },
        "compile": {
          "ref/dotnet/System.Runtime.Extensions.dll": {}
        }
      },
      "System.Runtime.Handles/4.0.0-beta-23109": {
        "dependencies": {
          "System.Runtime": "4.0.0-beta-23109"
        },
        "compile": {
          "ref/dotnet/System.Runtime.Handles.dll": {}
        }
      },
      "System.Runtime.InteropServices/4.0.20-beta-23109": {
        "dependencies": {
          "System.Runtime": "4.0.0-beta-23109",
          "System.Reflection": "4.0.0-beta-23109",
          "System.Reflection.Primitives": "4.0.0-beta-23109",
          "System.Runtime.Handles": "4.0.0-beta-23109"
        },
        "compile": {
          "ref/dotnet/System.Runtime.InteropServices.dll": {}
        }
      },
      "System.Text.Encoding/4.0.0-beta-23109": {
        "dependencies": {
          "System.Runtime": "4.0.0-beta-23109"
        },
        "compile": {
          "ref/dotnet/System.Text.Encoding.dll": {}
        }
      },
      "System.Text.RegularExpressions/4.0.10-beta-23109": {
        "dependencies": {
          "System.Runtime": "4.0.20-beta-23109",
          "System.Resources.ResourceManager": "4.0.0-beta-23109",
          "System.Collections": "4.0.10-beta-23109",
          "System.Globalization": "4.0.10-beta-23109",
          "System.Runtime.Extensions": "4.0.10-beta-23109",
          "System.Threading": "4.0.10-beta-23109"
        },
        "compile": {
          "ref/dotnet/System.Text.RegularExpressions.dll": {}
        },
        "runtime": {
          "lib/dotnet/System.Text.RegularExpressions.dll": {}
        }
      },
      "System.Threading/4.0.10-beta-23109": {
        "dependencies": {
          "System.Runtime": "4.0.0-beta-23109",
          "System.Threading.Tasks": "4.0.0-beta-23109"
        },
        "compile": {
          "ref/dotnet/System.Threading.dll": {}
        }
      },
      "System.Threading.Tasks/4.0.10-beta-23109": {
        "dependencies": {
          "System.Runtime": "4.0.0-beta-23109"
        },
        "compile": {
          "ref/dotnet/System.Threading.Tasks.dll": {}
        }
      }
    }
  },
  "libraries": {
    "Microsoft.CSharp/4.0.0-beta-23109": {
      "serviceable": true,
      "sha512": "MO4Lu8aMS1vL4Omp/gIMl2hr4sdV1l99p6xhAExGnS3MlFEa5JYPDL5mpdeg/osDH+1gAhb11xMJTYP7Ya3cAA==",
      "files": [
        "Microsoft.CSharp.4.0.0-beta-23109.nupkg",
        "Microsoft.CSharp.4.0.0-beta-23109.nupkg.sha512",
        "Microsoft.CSharp.nuspec",
        "lib/dotnet/Microsoft.CSharp.dll",
        "lib/net45/_._",
        "lib/netcore50/Microsoft.CSharp.dll",
        "lib/win8/_._",
        "lib/wp80/_._",
        "lib/wpa81/_._",
        "ref/dotnet/Microsoft.CSharp.dll",
        "ref/dotnet/Microsoft.CSharp.xml",
        "ref/dotnet/de/Microsoft.CSharp.xml",
        "ref/dotnet/es/Microsoft.CSharp.xml",
        "ref/dotnet/fr/Microsoft.CSharp.xml",
        "ref/dotnet/it/Microsoft.CSharp.xml",
        "ref/dotnet/ja/Microsoft.CSharp.xml",
        "ref/dotnet/ko/Microsoft.CSharp.xml",
        "ref/dotnet/ru/Microsoft.CSharp.xml",
        "ref/dotnet/zh-hans/Microsoft.CSharp.xml",
        "ref/dotnet/zh-hant/Microsoft.CSharp.xml",
        "ref/net45/_._",
        "ref/netcore50/Microsoft.CSharp.dll",
        "ref/netcore50/Microsoft.CSharp.xml",
        "ref/win8/_._",
        "ref/wp80/_._",
        "ref/wpa81/_._"
      ]
    },
    "System.Collections/4.0.10-beta-23109": {
      "serviceable": true,
      "sha512": "2/VX+2QEyyIpvGDzuIXX8V0vSl/Llt673DR48nNmeA6BoMuwL4Eu4F1Meh9fPp80nhcjifqVK8g7/UQDn/0PFw==",
      "files": [
        "System.Collections.4.0.10-beta-23109.nupkg",
        "System.Collections.4.0.10-beta-23109.nupkg.sha512",
        "System.Collections.nuspec",
        "lib/DNXCore50/System.Collections.dll",
        "lib/net46/_._",
        "lib/netcore50/System.Collections.dll",
        "ref/dotnet/System.Collections.dll",
        "ref/dotnet/System.Collections.xml",
        "ref/dotnet/de/System.Collections.xml",
        "ref/dotnet/es/System.Collections.xml",
        "ref/dotnet/fr/System.Collections.xml",
        "ref/dotnet/it/System.Collections.xml",
        "ref/dotnet/ja/System.Collections.xml",
        "ref/dotnet/ko/System.Collections.xml",
        "ref/dotnet/ru/System.Collections.xml",
        "ref/dotnet/zh-hans/System.Collections.xml",
        "ref/dotnet/zh-hant/System.Collections.xml",
        "ref/net46/_._",
        "runtimes/win8-aot/lib/netcore50/System.Collections.dll"
      ]
    },
    "System.Collections.Concurrent/4.0.10-beta-23109": {
      "serviceable": true,
      "sha512": "fRXR5y4dg9zPovFpSQZkc6gnyMNlQJVQ8lKqPDPFSIelhqWxv2VyY87s5Vd9ViGwKrFwekDwCQFug9ny8qCHuA==",
      "files": [
        "System.Collections.Concurrent.4.0.10-beta-23109.nupkg",
        "System.Collections.Concurrent.4.0.10-beta-23109.nupkg.sha512",
        "System.Collections.Concurrent.nuspec",
        "lib/dotnet/System.Collections.Concurrent.dll",
        "lib/net46/_._",
        "ref/dotnet/System.Collections.Concurrent.dll",
        "ref/dotnet/System.Collections.Concurrent.xml",
        "ref/dotnet/de/System.Collections.Concurrent.xml",
        "ref/dotnet/es/System.Collections.Concurrent.xml",
        "ref/dotnet/fr/System.Collections.Concurrent.xml",
        "ref/dotnet/it/System.Collections.Concurrent.xml",
        "ref/dotnet/ja/System.Collections.Concurrent.xml",
        "ref/dotnet/ko/System.Collections.Concurrent.xml",
        "ref/dotnet/ru/System.Collections.Concurrent.xml",
        "ref/dotnet/zh-hans/System.Collections.Concurrent.xml",
        "ref/dotnet/zh-hant/System.Collections.Concurrent.xml",
        "ref/net46/_._"
      ]
    },
    "System.ComponentModel/4.0.0-beta-23109": {
      "serviceable": true,
      "sha512": "JFzHUvX28tQbud0c9AP+SFeOroBG9x7tgc0OYu0Z5nQotnIiwP5nHXq9DoK3N2y0MoRUt8jy2FwkRMAYgiQuNQ==",
      "files": [
        "System.ComponentModel.4.0.0-beta-23109.nupkg",
        "System.ComponentModel.4.0.0-beta-23109.nupkg.sha512",
        "System.ComponentModel.nuspec",
        "lib/dotnet/System.ComponentModel.dll",
        "lib/net45/_._",
        "lib/netcore50/System.ComponentModel.dll",
        "lib/win8/_._",
        "lib/wp80/_._",
        "lib/wpa81/_._",
        "ref/dotnet/System.ComponentModel.dll",
        "ref/dotnet/System.ComponentModel.xml",
        "ref/dotnet/de/System.ComponentModel.xml",
        "ref/dotnet/es/System.ComponentModel.xml",
        "ref/dotnet/fr/System.ComponentModel.xml",
        "ref/dotnet/it/System.ComponentModel.xml",
        "ref/dotnet/ja/System.ComponentModel.xml",
        "ref/dotnet/ko/System.ComponentModel.xml",
        "ref/dotnet/ru/System.ComponentModel.xml",
        "ref/dotnet/zh-hans/System.ComponentModel.xml",
        "ref/dotnet/zh-hant/System.ComponentModel.xml",
        "ref/net45/_._",
        "ref/netcore50/System.ComponentModel.dll",
        "ref/netcore50/System.ComponentModel.xml",
        "ref/win8/_._",
        "ref/wp80/_._",
        "ref/wpa81/_._"
      ]
    },
    "System.Diagnostics.Debug/4.0.10-beta-23109": {
      "serviceable": true,
      "sha512": "woJsNwCtAqYac5zp+6Wy40HAp7kYr8zhaFvHl3gECjQf+VGeGYaHgDV1ATVcyMG1h6XvmX0wtmD5Qds51CRJoA==",
      "files": [
        "System.Diagnostics.Debug.4.0.10-beta-23109.nupkg",
        "System.Diagnostics.Debug.4.0.10-beta-23109.nupkg.sha512",
        "System.Diagnostics.Debug.nuspec",
        "lib/DNXCore50/System.Diagnostics.Debug.dll",
        "lib/net46/_._",
        "lib/netcore50/System.Diagnostics.Debug.dll",
        "ref/dotnet/System.Diagnostics.Debug.dll",
        "ref/dotnet/System.Diagnostics.Debug.xml",
        "ref/dotnet/de/System.Diagnostics.Debug.xml",
        "ref/dotnet/es/System.Diagnostics.Debug.xml",
        "ref/dotnet/fr/System.Diagnostics.Debug.xml",
        "ref/dotnet/it/System.Diagnostics.Debug.xml",
        "ref/dotnet/ja/System.Diagnostics.Debug.xml",
        "ref/dotnet/ko/System.Diagnostics.Debug.xml",
        "ref/dotnet/ru/System.Diagnostics.Debug.xml",
        "ref/dotnet/zh-hans/System.Diagnostics.Debug.xml",
        "ref/dotnet/zh-hant/System.Diagnostics.Debug.xml",
        "ref/net46/_._",
        "runtimes/win8-aot/lib/netcore50/System.Diagnostics.Debug.dll"
      ]
    },
    "System.Diagnostics.Tools/4.0.0-beta-23109": {
      "serviceable": true,
      "sha512": "6tFdP3p3SV6DZOagwW5ThfUF+zp5pUIyW4CY2K4B2RxV6HGVyY/8J2EuZGrcEP3wdO5fXnb9MmdOZa5Tn01Hmg==",
      "files": [
        "System.Diagnostics.Tools.4.0.0-beta-23109.nupkg",
        "System.Diagnostics.Tools.4.0.0-beta-23109.nupkg.sha512",
        "System.Diagnostics.Tools.nuspec",
        "lib/DNXCore50/System.Diagnostics.Tools.dll",
        "lib/net45/_._",
        "lib/netcore50/System.Diagnostics.Tools.dll",
        "lib/win8/_._",
        "lib/wp80/_._",
        "lib/wpa81/_._",
        "ref/dotnet/System.Diagnostics.Tools.dll",
        "ref/dotnet/System.Diagnostics.Tools.xml",
        "ref/dotnet/de/System.Diagnostics.Tools.xml",
        "ref/dotnet/es/System.Diagnostics.Tools.xml",
        "ref/dotnet/fr/System.Diagnostics.Tools.xml",
        "ref/dotnet/it/System.Diagnostics.Tools.xml",
        "ref/dotnet/ja/System.Diagnostics.Tools.xml",
        "ref/dotnet/ko/System.Diagnostics.Tools.xml",
        "ref/dotnet/ru/System.Diagnostics.Tools.xml",
        "ref/dotnet/zh-hans/System.Diagnostics.Tools.xml",
        "ref/dotnet/zh-hant/System.Diagnostics.Tools.xml",
        "ref/net45/_._",
        "ref/netcore50/System.Diagnostics.Tools.dll",
        "ref/netcore50/System.Diagnostics.Tools.xml",
        "ref/win8/_._",
        "ref/wp80/_._",
        "ref/wpa81/_._",
        "runtimes/win8-aot/lib/netcore50/System.Diagnostics.Tools.dll"
      ]
    },
    "System.Diagnostics.Tracing/4.0.20-beta-23109": {
      "serviceable": true,
      "sha512": "sNauLSBFewFLjULHeplEr7FCmmfPbcc1jfz1Mynjy445bYiP/IW1q9X14a//oV/uQG7p82S9qHyfPxoxmt3pxQ==",
      "files": [
        "System.Diagnostics.Tracing.4.0.20-beta-23109.nupkg",
        "System.Diagnostics.Tracing.4.0.20-beta-23109.nupkg.sha512",
        "System.Diagnostics.Tracing.nuspec",
        "lib/DNXCore50/System.Diagnostics.Tracing.dll",
        "lib/net46/_._",
        "lib/netcore50/System.Diagnostics.Tracing.dll",
        "ref/dotnet/System.Diagnostics.Tracing.dll",
        "ref/dotnet/System.Diagnostics.Tracing.xml",
        "ref/dotnet/de/System.Diagnostics.Tracing.xml",
        "ref/dotnet/es/System.Diagnostics.Tracing.xml",
        "ref/dotnet/fr/System.Diagnostics.Tracing.xml",
        "ref/dotnet/it/System.Diagnostics.Tracing.xml",
        "ref/dotnet/ja/System.Diagnostics.Tracing.xml",
        "ref/dotnet/ko/System.Diagnostics.Tracing.xml",
        "ref/dotnet/ru/System.Diagnostics.Tracing.xml",
        "ref/dotnet/zh-hans/System.Diagnostics.Tracing.xml",
        "ref/dotnet/zh-hant/System.Diagnostics.Tracing.xml",
        "ref/net46/_._",
        "runtimes/win8-aot/lib/netcore50/System.Diagnostics.Tracing.dll"
      ]
    },
    "System.Dynamic.Runtime/4.0.0-beta-23109": {
      "sha512": "nH2j/mWRcUME1Tz9tFXhf6zWGRVW5a5M+2bMG5GvudHv0SrbwfPGQBqwYCm5n1uQu68K1C59evXEq8BoMdXlcg==",
      "files": [
        "License.rtf",
        "System.Dynamic.Runtime.4.0.0-beta-23109.nupkg",
        "System.Dynamic.Runtime.4.0.0-beta-23109.nupkg.sha512",
        "System.Dynamic.Runtime.nuspec",
        "lib/net45/_._",
        "lib/win8/_._",
        "lib/wp80/_._",
        "lib/wpa81/_._",
        "ref/dotnet/System.Dynamic.Runtime.dll",
        "ref/dotnet/System.Dynamic.Runtime.xml",
        "ref/dotnet/de/System.Dynamic.Runtime.xml",
        "ref/dotnet/es/System.Dynamic.Runtime.xml",
        "ref/dotnet/fr/System.Dynamic.Runtime.xml",
        "ref/dotnet/it/System.Dynamic.Runtime.xml",
        "ref/dotnet/ja/System.Dynamic.Runtime.xml",
        "ref/dotnet/ko/System.Dynamic.Runtime.xml",
        "ref/dotnet/ru/System.Dynamic.Runtime.xml",
        "ref/dotnet/zh-hans/System.Dynamic.Runtime.xml",
        "ref/dotnet/zh-hant/System.Dynamic.Runtime.xml",
        "ref/net45/_._",
        "ref/netcore50/System.Dynamic.Runtime.dll",
        "ref/netcore50/System.Dynamic.Runtime.xml",
        "ref/netcore50/de/System.Dynamic.Runtime.xml",
        "ref/netcore50/es/System.Dynamic.Runtime.xml",
        "ref/netcore50/fr/System.Dynamic.Runtime.xml",
        "ref/netcore50/it/System.Dynamic.Runtime.xml",
        "ref/netcore50/ja/System.Dynamic.Runtime.xml",
        "ref/netcore50/ko/System.Dynamic.Runtime.xml",
        "ref/netcore50/ru/System.Dynamic.Runtime.xml",
        "ref/netcore50/zh-hans/System.Dynamic.Runtime.xml",
        "ref/netcore50/zh-hant/System.Dynamic.Runtime.xml",
        "ref/win8/_._",
        "ref/wp80/_._",
        "ref/wpa81/_._"
      ]
    },
    "System.Globalization/4.0.10-beta-23109": {
      "sha512": "l4QNrgLmC4KHGLcfriJ2EmsM2j18xefJzCnLU6YqVdBFaYzsJGwqmHyIr4nqw9DBjdWEtzdHLEbvpLeEay0ZWQ==",
      "files": [
        "System.Globalization.4.0.10-beta-23109.nupkg",
        "System.Globalization.4.0.10-beta-23109.nupkg.sha512",
        "System.Globalization.nuspec",
        "lib/DNXCore50/System.Globalization.dll",
        "lib/net46/_._",
        "lib/netcore50/System.Globalization.dll",
        "ref/dotnet/System.Globalization.dll",
        "ref/dotnet/System.Globalization.xml",
        "ref/dotnet/de/System.Globalization.xml",
        "ref/dotnet/es/System.Globalization.xml",
        "ref/dotnet/fr/System.Globalization.xml",
        "ref/dotnet/it/System.Globalization.xml",
        "ref/dotnet/ja/System.Globalization.xml",
        "ref/dotnet/ko/System.Globalization.xml",
        "ref/dotnet/ru/System.Globalization.xml",
        "ref/dotnet/zh-hans/System.Globalization.xml",
        "ref/dotnet/zh-hant/System.Globalization.xml",
        "ref/net46/_._",
        "runtimes/win8-aot/lib/netcore50/System.Globalization.dll"
      ]
    },
    "System.IO/4.0.0-beta-23109": {
      "sha512": "5hFYIKRlgbPyYa9NKvizmrCACEbzVRpgMf+lF6erYxa5P7lPcbbQEt9C3xBbvShBwqNNzkosB5kD5MeaNKAmww==",
      "files": [
        "License.rtf",
        "System.IO.4.0.0-beta-23109.nupkg",
        "System.IO.4.0.0-beta-23109.nupkg.sha512",
        "System.IO.nuspec",
        "lib/net45/_._",
        "lib/win8/_._",
        "lib/wp80/_._",
        "lib/wpa81/_._",
        "ref/dotnet/System.IO.dll",
        "ref/dotnet/System.IO.xml",
        "ref/dotnet/de/System.IO.xml",
        "ref/dotnet/es/System.IO.xml",
        "ref/dotnet/fr/System.IO.xml",
        "ref/dotnet/it/System.IO.xml",
        "ref/dotnet/ja/System.IO.xml",
        "ref/dotnet/ko/System.IO.xml",
        "ref/dotnet/ru/System.IO.xml",
        "ref/dotnet/zh-hans/System.IO.xml",
        "ref/dotnet/zh-hant/System.IO.xml",
        "ref/net45/_._",
        "ref/netcore50/System.IO.dll",
        "ref/netcore50/System.IO.xml",
        "ref/netcore50/de/System.IO.xml",
        "ref/netcore50/es/System.IO.xml",
        "ref/netcore50/fr/System.IO.xml",
        "ref/netcore50/it/System.IO.xml",
        "ref/netcore50/ja/System.IO.xml",
        "ref/netcore50/ko/System.IO.xml",
        "ref/netcore50/ru/System.IO.xml",
        "ref/netcore50/zh-hans/System.IO.xml",
        "ref/netcore50/zh-hant/System.IO.xml",
        "ref/win8/_._",
        "ref/wp80/_._",
        "ref/wpa81/_._"
      ]
    },
    "System.Linq/4.0.0-beta-23109": {
      "serviceable": true,
      "sha512": "NN0sQlEAjYDdMW5SU8p75niORiKwME2hRac30HB1QVUSuMtDs/easUBMJKGnXRHmxcrdwvHApfJOiH1tZ6eTbQ==",
      "files": [
        "System.Linq.4.0.0-beta-23109.nupkg",
        "System.Linq.4.0.0-beta-23109.nupkg.sha512",
        "System.Linq.nuspec",
        "lib/dotnet/System.Linq.dll",
        "lib/net45/_._",
        "lib/netcore50/System.Linq.dll",
        "lib/win8/_._",
        "lib/wp80/_._",
        "lib/wpa81/_._",
        "ref/dotnet/System.Linq.dll",
        "ref/dotnet/System.Linq.xml",
        "ref/dotnet/de/System.Linq.xml",
        "ref/dotnet/es/System.Linq.xml",
        "ref/dotnet/fr/System.Linq.xml",
        "ref/dotnet/it/System.Linq.xml",
        "ref/dotnet/ja/System.Linq.xml",
        "ref/dotnet/ko/System.Linq.xml",
        "ref/dotnet/ru/System.Linq.xml",
        "ref/dotnet/zh-hans/System.Linq.xml",
        "ref/dotnet/zh-hant/System.Linq.xml",
        "ref/net45/_._",
        "ref/netcore50/System.Linq.dll",
        "ref/netcore50/System.Linq.xml",
        "ref/win8/_._",
        "ref/wp80/_._",
        "ref/wpa81/_._"
      ]
    },
    "System.Linq.Expressions/4.0.10-beta-23109": {
      "serviceable": true,
      "sha512": "cy+sQJW809QnFHIXt5Y/If45u362gwiNqHldnJS70l7VCjyR4Bo3UgZMZl+bowSupWxqXk69cwCQhRUyFu2hVw==",
      "files": [
        "runtime.json",
        "System.Linq.Expressions.4.0.10-beta-23109.nupkg",
        "System.Linq.Expressions.4.0.10-beta-23109.nupkg.sha512",
        "System.Linq.Expressions.nuspec",
        "lib/DNXCore50/System.Linq.Expressions.dll",
        "lib/net46/_._",
        "lib/netcore50/System.Linq.Expressions.dll",
        "ref/dotnet/System.Linq.Expressions.dll",
        "ref/dotnet/System.Linq.Expressions.xml",
        "ref/dotnet/de/System.Linq.Expressions.xml",
        "ref/dotnet/es/System.Linq.Expressions.xml",
        "ref/dotnet/fr/System.Linq.Expressions.xml",
        "ref/dotnet/it/System.Linq.Expressions.xml",
        "ref/dotnet/ja/System.Linq.Expressions.xml",
        "ref/dotnet/ko/System.Linq.Expressions.xml",
        "ref/dotnet/ru/System.Linq.Expressions.xml",
        "ref/dotnet/zh-hans/System.Linq.Expressions.xml",
        "ref/dotnet/zh-hant/System.Linq.Expressions.xml",
        "ref/net46/_._",
        "runtimes/win8-aot/lib/netcore50/System.Linq.Expressions.dll"
      ]
    },
    "System.ObjectModel/4.0.10-beta-23109": {
      "serviceable": true,
      "sha512": "mnrhXE8nT5mX/ndEJ5BsdLCgN6CofKiwQvr9Olsp/s3crY5/lXYM73N2bNSvsFcHD1o0XhaCOn18Vekv6SYTpg==",
      "files": [
        "System.ObjectModel.4.0.10-beta-23109.nupkg",
        "System.ObjectModel.4.0.10-beta-23109.nupkg.sha512",
        "System.ObjectModel.nuspec",
        "lib/dotnet/System.ObjectModel.dll",
        "lib/net46/_._",
        "ref/dotnet/System.ObjectModel.dll",
        "ref/dotnet/System.ObjectModel.xml",
        "ref/dotnet/de/System.ObjectModel.xml",
        "ref/dotnet/es/System.ObjectModel.xml",
        "ref/dotnet/fr/System.ObjectModel.xml",
        "ref/dotnet/it/System.ObjectModel.xml",
        "ref/dotnet/ja/System.ObjectModel.xml",
        "ref/dotnet/ko/System.ObjectModel.xml",
        "ref/dotnet/ru/System.ObjectModel.xml",
        "ref/dotnet/zh-hans/System.ObjectModel.xml",
        "ref/dotnet/zh-hant/System.ObjectModel.xml",
        "ref/net46/_._"
      ]
    },
    "System.Reflection/4.0.10-beta-23109": {
      "sha512": "aeXO8gjPb46LaP727cXDcCZ2mZoMxguq2UhE25wJoO1Je8Q8D2JFonNk85oVlgXCdEM6XgrtRnsnhvj8PmTBNg==",
      "files": [
        "System.Reflection.4.0.10-beta-23109.nupkg",
        "System.Reflection.4.0.10-beta-23109.nupkg.sha512",
        "System.Reflection.nuspec",
        "lib/DNXCore50/System.Reflection.dll",
        "lib/net46/_._",
        "lib/netcore50/System.Reflection.dll",
        "ref/dotnet/System.Reflection.dll",
        "ref/dotnet/System.Reflection.xml",
        "ref/dotnet/de/System.Reflection.xml",
        "ref/dotnet/es/System.Reflection.xml",
        "ref/dotnet/fr/System.Reflection.xml",
        "ref/dotnet/it/System.Reflection.xml",
        "ref/dotnet/ja/System.Reflection.xml",
        "ref/dotnet/ko/System.Reflection.xml",
        "ref/dotnet/ru/System.Reflection.xml",
        "ref/dotnet/zh-hans/System.Reflection.xml",
        "ref/dotnet/zh-hant/System.Reflection.xml",
        "ref/net46/_._",
        "runtimes/win8-aot/lib/netcore50/System.Reflection.dll"
      ]
    },
    "System.Reflection.Extensions/4.0.0-beta-23109": {
      "serviceable": true,
      "sha512": "sXo3+qJ7TukCF/rDFYKjEog4iVb75dXJztu/lkvhMHgYnviPSbi9zg78FQUFhB6BOvntwnknrgNJhhtl3x9a7A==",
      "files": [
        "System.Reflection.Extensions.4.0.0-beta-23109.nupkg",
        "System.Reflection.Extensions.4.0.0-beta-23109.nupkg.sha512",
        "System.Reflection.Extensions.nuspec",
        "lib/DNXCore50/System.Reflection.Extensions.dll",
        "lib/net45/_._",
        "lib/netcore50/System.Reflection.Extensions.dll",
        "lib/win8/_._",
        "lib/wp80/_._",
        "lib/wpa81/_._",
        "ref/dotnet/System.Reflection.Extensions.dll",
        "ref/dotnet/System.Reflection.Extensions.xml",
        "ref/dotnet/de/System.Reflection.Extensions.xml",
        "ref/dotnet/es/System.Reflection.Extensions.xml",
        "ref/dotnet/fr/System.Reflection.Extensions.xml",
        "ref/dotnet/it/System.Reflection.Extensions.xml",
        "ref/dotnet/ja/System.Reflection.Extensions.xml",
        "ref/dotnet/ko/System.Reflection.Extensions.xml",
        "ref/dotnet/ru/System.Reflection.Extensions.xml",
        "ref/dotnet/zh-hans/System.Reflection.Extensions.xml",
        "ref/dotnet/zh-hant/System.Reflection.Extensions.xml",
        "ref/net45/_._",
        "ref/netcore50/System.Reflection.Extensions.dll",
        "ref/netcore50/System.Reflection.Extensions.xml",
        "ref/win8/_._",
        "ref/wp80/_._",
        "ref/wpa81/_._",
        "runtimes/win8-aot/lib/netcore50/System.Reflection.Extensions.dll"
      ]
    },
    "System.Reflection.Primitives/4.0.0-beta-23109": {
      "serviceable": true,
      "sha512": "R5oBDNgUtSV9KTPCxwHWiTyryX/9mngnPbLWwFOEF5xcNd3Qlu6/3LiauGsIzGtXV8vOpRl9tfyIFy8t4ix4Gw==",
      "files": [
        "System.Reflection.Primitives.4.0.0-beta-23109.nupkg",
        "System.Reflection.Primitives.4.0.0-beta-23109.nupkg.sha512",
        "System.Reflection.Primitives.nuspec",
        "lib/DNXCore50/System.Reflection.Primitives.dll",
        "lib/net45/_._",
        "lib/netcore50/System.Reflection.Primitives.dll",
        "lib/win8/_._",
        "lib/wp80/_._",
        "lib/wpa81/_._",
        "ref/dotnet/System.Reflection.Primitives.dll",
        "ref/dotnet/System.Reflection.Primitives.xml",
        "ref/dotnet/de/System.Reflection.Primitives.xml",
        "ref/dotnet/es/System.Reflection.Primitives.xml",
        "ref/dotnet/fr/System.Reflection.Primitives.xml",
        "ref/dotnet/it/System.Reflection.Primitives.xml",
        "ref/dotnet/ja/System.Reflection.Primitives.xml",
        "ref/dotnet/ko/System.Reflection.Primitives.xml",
        "ref/dotnet/ru/System.Reflection.Primitives.xml",
        "ref/dotnet/zh-hans/System.Reflection.Primitives.xml",
        "ref/dotnet/zh-hant/System.Reflection.Primitives.xml",
        "ref/net45/_._",
        "ref/netcore50/System.Reflection.Primitives.dll",
        "ref/netcore50/System.Reflection.Primitives.xml",
        "ref/win8/_._",
        "ref/wp80/_._",
        "ref/wpa81/_._",
        "runtimes/win8-aot/lib/netcore50/System.Reflection.Primitives.dll"
      ]
    },
    "System.Reflection.TypeExtensions/4.0.0-beta-23109": {
      "serviceable": true,
      "sha512": "lTuPMxeoT/Jqb1QtsIuSomLiJpQP3Y4DqqxLPncrMvLrejwdF25QSbhXdx5twgvBDqwSVL8wYtqiOqKe02u7FA==",
      "files": [
        "System.Reflection.TypeExtensions.4.0.0-beta-23109.nupkg",
        "System.Reflection.TypeExtensions.4.0.0-beta-23109.nupkg.sha512",
        "System.Reflection.TypeExtensions.nuspec",
        "lib/DNXCore50/System.Reflection.TypeExtensions.dll",
        "lib/net46/System.Reflection.TypeExtensions.dll",
        "lib/netcore50/System.Reflection.TypeExtensions.dll",
        "ref/dotnet/System.Reflection.TypeExtensions.dll",
        "ref/dotnet/System.Reflection.TypeExtensions.xml",
        "ref/dotnet/de/System.Reflection.TypeExtensions.xml",
        "ref/dotnet/es/System.Reflection.TypeExtensions.xml",
        "ref/dotnet/fr/System.Reflection.TypeExtensions.xml",
        "ref/dotnet/it/System.Reflection.TypeExtensions.xml",
        "ref/dotnet/ja/System.Reflection.TypeExtensions.xml",
        "ref/dotnet/ko/System.Reflection.TypeExtensions.xml",
        "ref/dotnet/ru/System.Reflection.TypeExtensions.xml",
        "ref/dotnet/zh-hans/System.Reflection.TypeExtensions.xml",
        "ref/dotnet/zh-hant/System.Reflection.TypeExtensions.xml",
        "ref/net46/System.Reflection.TypeExtensions.dll",
        "runtimes/win8-aot/lib/netcore50/System.Reflection.TypeExtensions.dll"
      ]
    },
    "System.Resources.ResourceManager/4.0.0-beta-23109": {
      "serviceable": true,
      "sha512": "S7Hx7w3xzlwxzyIIvcpiFDM/gIu317Nkn4PC0IzQFMBP1pC/RH7OI8AVkpuqeXMqqWoo3pz/Kvcsd2GSzDmQew==",
      "files": [
        "System.Resources.ResourceManager.4.0.0-beta-23109.nupkg",
        "System.Resources.ResourceManager.4.0.0-beta-23109.nupkg.sha512",
        "System.Resources.ResourceManager.nuspec",
        "lib/DNXCore50/System.Resources.ResourceManager.dll",
        "lib/net45/_._",
        "lib/netcore50/System.Resources.ResourceManager.dll",
        "lib/win8/_._",
        "lib/wp80/_._",
        "lib/wpa81/_._",
        "ref/dotnet/System.Resources.ResourceManager.dll",
        "ref/dotnet/System.Resources.ResourceManager.xml",
        "ref/dotnet/de/System.Resources.ResourceManager.xml",
        "ref/dotnet/es/System.Resources.ResourceManager.xml",
        "ref/dotnet/fr/System.Resources.ResourceManager.xml",
        "ref/dotnet/it/System.Resources.ResourceManager.xml",
        "ref/dotnet/ja/System.Resources.ResourceManager.xml",
        "ref/dotnet/ko/System.Resources.ResourceManager.xml",
        "ref/dotnet/ru/System.Resources.ResourceManager.xml",
        "ref/dotnet/zh-hans/System.Resources.ResourceManager.xml",
        "ref/dotnet/zh-hant/System.Resources.ResourceManager.xml",
        "ref/net45/_._",
        "ref/netcore50/System.Resources.ResourceManager.dll",
        "ref/netcore50/System.Resources.ResourceManager.xml",
        "ref/win8/_._",
        "ref/wp80/_._",
        "ref/wpa81/_._",
        "runtimes/win8-aot/lib/netcore50/System.Resources.ResourceManager.dll"
      ]
    },
    "System.Runtime/4.0.20-beta-23109": {
      "serviceable": true,
      "sha512": "6usAb6nZEPKugl3z5JR/RZrouH5/340n3tM0lhRfxVE/k3B3Sfh/sHSPiAOorrZgGm4cIDDhXTCGJQSWYphu3g==",
      "files": [
        "System.Runtime.4.0.20-beta-23109.nupkg",
        "System.Runtime.4.0.20-beta-23109.nupkg.sha512",
        "System.Runtime.nuspec",
        "lib/DNXCore50/System.Runtime.dll",
        "lib/net46/_._",
        "lib/netcore50/System.Runtime.dll",
        "ref/dotnet/System.Runtime.dll",
        "ref/dotnet/System.Runtime.xml",
        "ref/dotnet/de/System.Runtime.xml",
        "ref/dotnet/es/System.Runtime.xml",
        "ref/dotnet/fr/System.Runtime.xml",
        "ref/dotnet/it/System.Runtime.xml",
        "ref/dotnet/ja/System.Runtime.xml",
        "ref/dotnet/ko/System.Runtime.xml",
        "ref/dotnet/ru/System.Runtime.xml",
        "ref/dotnet/zh-hans/System.Runtime.xml",
        "ref/dotnet/zh-hant/System.Runtime.xml",
        "ref/net46/_._",
        "runtimes/win8-aot/lib/netcore50/System.Runtime.dll"
      ]
    },
    "System.Runtime.Extensions/4.0.10-beta-23109": {
      "serviceable": true,
      "sha512": "JkRMtSY5YFGhP9eY7ZFIj40Ha5lGOwSxrk90k0ZAuIFn6qEPNe0NKu/C8laV7Cqy4Lv5IYzkVUGrfOqg3MOG9A==",
      "files": [
        "System.Runtime.Extensions.4.0.10-beta-23109.nupkg",
        "System.Runtime.Extensions.4.0.10-beta-23109.nupkg.sha512",
        "System.Runtime.Extensions.nuspec",
        "lib/DNXCore50/System.Runtime.Extensions.dll",
        "lib/net46/_._",
        "lib/netcore50/System.Runtime.Extensions.dll",
        "ref/dotnet/System.Runtime.Extensions.dll",
        "ref/dotnet/System.Runtime.Extensions.xml",
        "ref/dotnet/de/System.Runtime.Extensions.xml",
        "ref/dotnet/es/System.Runtime.Extensions.xml",
        "ref/dotnet/fr/System.Runtime.Extensions.xml",
        "ref/dotnet/it/System.Runtime.Extensions.xml",
        "ref/dotnet/ja/System.Runtime.Extensions.xml",
        "ref/dotnet/ko/System.Runtime.Extensions.xml",
        "ref/dotnet/ru/System.Runtime.Extensions.xml",
        "ref/dotnet/zh-hans/System.Runtime.Extensions.xml",
        "ref/dotnet/zh-hant/System.Runtime.Extensions.xml",
        "ref/net46/_._",
        "runtimes/win8-aot/lib/netcore50/System.Runtime.Extensions.dll"
      ]
    },
    "System.Runtime.Handles/4.0.0-beta-23109": {
      "serviceable": true,
      "sha512": "XfjBv5hxBDVXvgPzBXiMpHprnmd5trdBAG4o7DEi/3GPXIlety4G0sfmlxeiTr7njKr0wF4ERdLIfzPesS5PAw==",
      "files": [
        "System.Runtime.Handles.4.0.0-beta-23109.nupkg",
        "System.Runtime.Handles.4.0.0-beta-23109.nupkg.sha512",
        "System.Runtime.Handles.nuspec",
        "lib/DNXCore50/System.Runtime.Handles.dll",
        "lib/net46/_._",
        "lib/netcore50/System.Runtime.Handles.dll",
        "ref/dotnet/System.Runtime.Handles.dll",
        "ref/dotnet/System.Runtime.Handles.xml",
        "ref/dotnet/de/System.Runtime.Handles.xml",
        "ref/dotnet/es/System.Runtime.Handles.xml",
        "ref/dotnet/fr/System.Runtime.Handles.xml",
        "ref/dotnet/it/System.Runtime.Handles.xml",
        "ref/dotnet/ja/System.Runtime.Handles.xml",
        "ref/dotnet/ko/System.Runtime.Handles.xml",
        "ref/dotnet/ru/System.Runtime.Handles.xml",
        "ref/dotnet/zh-hans/System.Runtime.Handles.xml",
        "ref/dotnet/zh-hant/System.Runtime.Handles.xml",
        "ref/net46/_._",
        "runtimes/win8-aot/lib/netcore50/System.Runtime.Handles.dll"
      ]
    },
    "System.Runtime.InteropServices/4.0.20-beta-23109": {
      "serviceable": true,
      "sha512": "fxRLTR5kbqOZuSeT5ggVBYc6HIEGmEwh+Uw1ijp2qD3yMiMPmxvtI5aP5t0yZHEmwUrB37lGB+oaPpcXLH5Feg==",
      "files": [
        "System.Runtime.InteropServices.4.0.20-beta-23109.nupkg",
        "System.Runtime.InteropServices.4.0.20-beta-23109.nupkg.sha512",
        "System.Runtime.InteropServices.nuspec",
        "lib/DNXCore50/System.Runtime.InteropServices.dll",
        "lib/net46/_._",
        "lib/netcore50/System.Runtime.InteropServices.dll",
        "ref/dotnet/System.Runtime.InteropServices.dll",
        "ref/dotnet/System.Runtime.InteropServices.xml",
        "ref/dotnet/de/System.Runtime.InteropServices.xml",
        "ref/dotnet/es/System.Runtime.InteropServices.xml",
        "ref/dotnet/fr/System.Runtime.InteropServices.xml",
        "ref/dotnet/it/System.Runtime.InteropServices.xml",
        "ref/dotnet/ja/System.Runtime.InteropServices.xml",
        "ref/dotnet/ko/System.Runtime.InteropServices.xml",
        "ref/dotnet/ru/System.Runtime.InteropServices.xml",
        "ref/dotnet/zh-hans/System.Runtime.InteropServices.xml",
        "ref/dotnet/zh-hant/System.Runtime.InteropServices.xml",
        "ref/net46/_._",
        "runtimes/win8-aot/lib/netcore50/System.Runtime.InteropServices.dll"
      ]
    },
    "System.Text.Encoding/4.0.0-beta-23109": {
      "sha512": "LlQ07793RcpK1Dgs8jV7YizVv0F78iFyE7t1t/EPQGCA+gxdbFDsmCmlZ/Bbr6KR7KwoFePi+YEQGDDcNmV+8g==",
      "files": [
        "License.rtf",
        "System.Text.Encoding.4.0.0-beta-23109.nupkg",
        "System.Text.Encoding.4.0.0-beta-23109.nupkg.sha512",
        "System.Text.Encoding.nuspec",
        "lib/net45/_._",
        "lib/win8/_._",
        "lib/wp80/_._",
        "lib/wpa81/_._",
        "ref/dotnet/System.Text.Encoding.dll",
        "ref/dotnet/System.Text.Encoding.xml",
        "ref/dotnet/de/System.Text.Encoding.xml",
        "ref/dotnet/es/System.Text.Encoding.xml",
        "ref/dotnet/fr/System.Text.Encoding.xml",
        "ref/dotnet/it/System.Text.Encoding.xml",
        "ref/dotnet/ja/System.Text.Encoding.xml",
        "ref/dotnet/ko/System.Text.Encoding.xml",
        "ref/dotnet/ru/System.Text.Encoding.xml",
        "ref/dotnet/zh-hans/System.Text.Encoding.xml",
        "ref/dotnet/zh-hant/System.Text.Encoding.xml",
        "ref/net45/_._",
        "ref/netcore50/System.Text.Encoding.dll",
        "ref/netcore50/System.Text.Encoding.xml",
        "ref/netcore50/de/System.Text.Encoding.xml",
        "ref/netcore50/es/System.Text.Encoding.xml",
        "ref/netcore50/fr/System.Text.Encoding.xml",
        "ref/netcore50/it/System.Text.Encoding.xml",
        "ref/netcore50/ja/System.Text.Encoding.xml",
        "ref/netcore50/ko/System.Text.Encoding.xml",
        "ref/netcore50/ru/System.Text.Encoding.xml",
        "ref/netcore50/zh-hans/System.Text.Encoding.xml",
        "ref/netcore50/zh-hant/System.Text.Encoding.xml",
        "ref/win8/_._",
        "ref/wp80/_._",
        "ref/wpa81/_._"
      ]
    },
    "System.Text.RegularExpressions/4.0.10-beta-23109": {
      "serviceable": true,
      "sha512": "F+tfzB34KhZnjS3ActdL57CQVD9oYGhAZm8AREL+KvbJTh1Y8/tlyCyI2xoH6KdJzIPcXC50yu4OkHNbpcutEw==",
      "files": [
        "System.Text.RegularExpressions.4.0.10-beta-23109.nupkg",
        "System.Text.RegularExpressions.4.0.10-beta-23109.nupkg.sha512",
        "System.Text.RegularExpressions.nuspec",
        "lib/dotnet/System.Text.RegularExpressions.dll",
        "lib/net46/_._",
        "ref/dotnet/System.Text.RegularExpressions.dll",
        "ref/dotnet/System.Text.RegularExpressions.xml",
        "ref/dotnet/de/System.Text.RegularExpressions.xml",
        "ref/dotnet/es/System.Text.RegularExpressions.xml",
        "ref/dotnet/fr/System.Text.RegularExpressions.xml",
        "ref/dotnet/it/System.Text.RegularExpressions.xml",
        "ref/dotnet/ja/System.Text.RegularExpressions.xml",
        "ref/dotnet/ko/System.Text.RegularExpressions.xml",
        "ref/dotnet/ru/System.Text.RegularExpressions.xml",
        "ref/dotnet/zh-hans/System.Text.RegularExpressions.xml",
        "ref/dotnet/zh-hant/System.Text.RegularExpressions.xml",
        "ref/net46/_._"
      ]
    },
    "System.Threading/4.0.10-beta-23109": {
      "serviceable": true,
      "sha512": "TSViw+K20yh9DmwzZpvuCUc2m2ju1eVAJ10pTw2gB/aP4kkrX2nGf4A9BkwkxupPXFA2OtO9LbbEqdp4YbBnjQ==",
      "files": [
        "System.Threading.4.0.10-beta-23109.nupkg",
        "System.Threading.4.0.10-beta-23109.nupkg.sha512",
        "System.Threading.nuspec",
        "lib/DNXCore50/System.Threading.dll",
        "lib/net46/_._",
        "lib/netcore50/System.Threading.dll",
        "ref/dotnet/System.Threading.dll",
        "ref/dotnet/System.Threading.xml",
        "ref/dotnet/de/System.Threading.xml",
        "ref/dotnet/es/System.Threading.xml",
        "ref/dotnet/fr/System.Threading.xml",
        "ref/dotnet/it/System.Threading.xml",
        "ref/dotnet/ja/System.Threading.xml",
        "ref/dotnet/ko/System.Threading.xml",
        "ref/dotnet/ru/System.Threading.xml",
        "ref/dotnet/zh-hans/System.Threading.xml",
        "ref/dotnet/zh-hant/System.Threading.xml",
        "ref/net46/_._",
        "runtimes/win8-aot/lib/netcore50/System.Threading.dll"
      ]
    },
    "System.Threading.Tasks/4.0.10-beta-23109": {
      "serviceable": true,
      "sha512": "J7lBqLLy1A85KZUgFz0fS8u6BO+pnWun2OAkrNqcUQbgCiKDC9v92u9q6a6AB9znum+GCdzH3cyEftNtIVNd1Q==",
      "files": [
        "System.Threading.Tasks.4.0.10-beta-23109.nupkg",
        "System.Threading.Tasks.4.0.10-beta-23109.nupkg.sha512",
        "System.Threading.Tasks.nuspec",
        "lib/DNXCore50/System.Threading.Tasks.dll",
        "lib/net46/_._",
        "lib/netcore50/System.Threading.Tasks.dll",
        "ref/dotnet/System.Threading.Tasks.dll",
        "ref/dotnet/System.Threading.Tasks.xml",
        "ref/dotnet/de/System.Threading.Tasks.xml",
        "ref/dotnet/es/System.Threading.Tasks.xml",
        "ref/dotnet/fr/System.Threading.Tasks.xml",
        "ref/dotnet/it/System.Threading.Tasks.xml",
        "ref/dotnet/ja/System.Threading.Tasks.xml",
        "ref/dotnet/ko/System.Threading.Tasks.xml",
        "ref/dotnet/ru/System.Threading.Tasks.xml",
        "ref/dotnet/zh-hans/System.Threading.Tasks.xml",
        "ref/dotnet/zh-hant/System.Threading.Tasks.xml",
        "ref/net46/_._",
        "runtimes/win8-aot/lib/netcore50/System.Threading.Tasks.dll"
      ]
    }
  },
  "projectFileDependencyGroups": {
    "": [],
    ".NETFramework,Version=v4.5": [
      "fx/System >= 4.0.0.0",
      "fx/System.Core >= 4.0.0.0",
      "fx/System.Linq >= 4.0.0.0",
      "fx/Microsoft.CSharp >= 4.0.0.0"
    ],
    ".NETCore,Version=v4.5": [
      "fx/System >= 4.0.0.0",
      "fx/System.Core >= 4.0.0.0",
      "fx/System.Linq >= 4.0.0.0",
      "fx/System.Reflection >= 4.0.0.0",
      "fx/System.Reflection.Extensions >= 4.0.0.0",
      "fx/System.Reflection.Primitives >= 4.0.0.0",
      "fx/System.Runtime >= 4.0.0.0",
      "fx/Microsoft.CSharp >= 4.0.0.0"
    ],
    ".NETPlatform,Version=v5.0": [
      "System.Collections >= 4.0.10-beta-*",
      "System.Collections.Concurrent >= 4.0.10-beta-*",
      "System.ComponentModel >= 4.0.0-beta-*",
      "System.Diagnostics.Debug >= 4.0.10-beta-*",
      "System.Diagnostics.Tools >= 4.0.0-beta-*",
      "System.Linq >= 4.0.0-beta-*",
      "System.Linq.Expressions >= 4.0.10-beta-*",
      "System.Reflection >= 4.0.10-beta-*",
      "System.Reflection.Extensions >= 4.0.0-beta-*",
      "System.Reflection.Primitives >= 4.0.0-beta-*",
      "System.Reflection.TypeExtensions >= 4.0.0-beta-*",
      "System.Resources.ResourceManager >= 4.0.0-beta-*",
      "System.Runtime >= 4.0.20-beta-*",
      "System.Text.RegularExpressions >= 4.0.10-beta-*",
      "System.Threading >= 4.0.10-beta-*",
      "Microsoft.CSharp >= 4.0.0-beta-*"
    ]
  }
}